folder_tree/__init__.py
folder_tree/tree.py
folder_tree-1.0.0.dist-info/METADATA
folder_tree-1.0.0.dist-info/WHEEL
folder_tree-1.0.0.dist-info/entry_points.txt
folder_tree-1.0.0.dist-info/top_level.txt
folder_tree-1.0.0.dist-info/RECORD
