Metadata-Version: 2.1
Name: folder-tree
Version: 1.0.0
Summary: A package to display folder structures in a tree format
Author: Sanosh
Requires-Python: >=3.6
